setup.py
bgdistribution.egg-info/PKG-INFO
bgdistribution.egg-info/SOURCES.txt
bgdistribution.egg-info/dependency_links.txt
bgdistribution.egg-info/not-zip-safe
bgdistribution.egg-info/top_level.txt
distributions/Binomialdistribution.py
distributions/Gaussiandistribution.py
distributions/Generaldistribution.py
distributions/__init__.py